dottoml/__init__.py
dottoml/main.py
dottoml-0.2.0.dist-info/LICENSE
dottoml-0.2.0.dist-info/METADATA
dottoml-0.2.0.dist-info/WHEEL
dottoml-0.2.0.dist-info/RECORD
