Metadata-Version: 2.1
Name: dottoml
Version: 0.2.0
Summary: Environment in TOML format.
Home-page: https://github.com/olivetree123/dottoml
License: MIT
Author: gaojian
Author-email: olivetree123@163.com
Requires-Python: >=3.8,<4.0
Classifier: License :: OSI Approved :: MIT License
Classifier: Programming Language :: Python :: 3
Classifier: Programming Language :: Python :: 3.8
Classifier: Programming Language :: Python :: 3.9
Classifier: Programming Language :: Python :: 3.10
Classifier: Programming Language :: Python :: 3.11
Classifier: Programming Language :: Python :: 3.12
Classifier: Programming Language :: Python :: 3.13
Requires-Dist: tomli (==2.0.1)
Project-URL: Documentation, https://github.com/olivetree123/dottoml
